loquax/__init__.py
loquax/abstractions/__init__.py
loquax/abstractions/constants.py
loquax/abstractions/linguistic_entities.py
loquax/abstractions/phonology.py
loquax/abstractions/syllabification.py
loquax/languages/__init__.py
loquax/languages/latin.py
loquax/languages/latin_conf/__init__.py
loquax/languages/latin_conf/constants.py
loquax/languages/latin_conf/rules.py
loquax/languages/latin_conf/tokenizer.py
loquax/text_processing/__init__.py
loquax/text_processing/commons.py
loquax/text_processing/processing.py
loquax-0.1.5.dist-info/LICENSE
loquax-0.1.5.dist-info/METADATA
loquax-0.1.5.dist-info/WHEEL
loquax-0.1.5.dist-info/top_level.txt
loquax-0.1.5.dist-info/RECORD
