Metadata-Version: 2.1
Name: loquax
Version: 0.1.5
Summary: A Classical Phonology framework
Home-page: https://github.com/mattlianje/loquax
Author: Matthieu Court
Author-email: matthieu.court@protonmail.com
License: UNKNOWN
Platform: UNKNOWN
Classifier: Development Status :: 3 - Alpha
Classifier: Intended Audience :: Science/Research
Classifier: License :: OSI Approved :: GNU General Public License v3 (GPLv3)
Classifier: Programming Language :: Python :: 3.10
Requires-Python: >=3.10
License-File: LICENSE
